rcl_yaml_param_parser/_dummy.cpython-310-x86_64-linux-gnu.so
ros_rcl_yaml_param_parser-10.1.3.data/data/include/rcl_yaml_param_parser/rcl_yaml_param_parser/parser.h
ros_rcl_yaml_param_parser-10.1.3.data/data/include/rcl_yaml_param_parser/rcl_yaml_param_parser/types.h
ros_rcl_yaml_param_parser-10.1.3.data/data/include/rcl_yaml_param_parser/rcl_yaml_param_parser/version.h
ros_rcl_yaml_param_parser-10.1.3.data/data/include/rcl_yaml_param_parser/rcl_yaml_param_parser/visibility_control.h
ros_rcl_yaml_param_parser-10.1.3.data/data/lib/librcl_yaml_param_parser.so
ros_rcl_yaml_param_parser-10.1.3.data/data/share/ament_index/resource_index/package_run_dependencies/rcl_yaml_param_parser
ros_rcl_yaml_param_parser-10.1.3.data/data/share/ament_index/resource_index/packages/rcl_yaml_param_parser
ros_rcl_yaml_param_parser-10.1.3.data/data/share/ament_index/resource_index/parent_prefix_path/rcl_yaml_param_parser
ros_rcl_yaml_param_parser-10.1.3.data/data/share/rcl_yaml_param_parser/local_setup.bash
ros_rcl_yaml_param_parser-10.1.3.data/data/share/rcl_yaml_param_parser/local_setup.dsv
ros_rcl_yaml_param_parser-10.1.3.data/data/share/rcl_yaml_param_parser/local_setup.sh
ros_rcl_yaml_param_parser-10.1.3.data/data/share/rcl_yaml_param_parser/local_setup.zsh
ros_rcl_yaml_param_parser-10.1.3.data/data/share/rcl_yaml_param_parser/package.dsv
ros_rcl_yaml_param_parser-10.1.3.data/data/share/rcl_yaml_param_parser/package.xml
ros_rcl_yaml_param_parser-10.1.3.data/data/share/rcl_yaml_param_parser/cmake/ament_cmake_export_dependencies-extras.cmake
ros_rcl_yaml_param_parser-10.1.3.data/data/share/rcl_yaml_param_parser/cmake/ament_cmake_export_include_directories-extras.cmake
ros_rcl_yaml_param_parser-10.1.3.data/data/share/rcl_yaml_param_parser/cmake/ament_cmake_export_libraries-extras.cmake
ros_rcl_yaml_param_parser-10.1.3.data/data/share/rcl_yaml_param_parser/cmake/ament_cmake_export_targets-extras.cmake
ros_rcl_yaml_param_parser-10.1.3.dist-info/METADATA
ros_rcl_yaml_param_parser-10.1.3.dist-info/WHEEL
ros_rcl_yaml_param_parser-10.1.3.dist-info/top_level.txt
ros_rcl_yaml_param_parser-10.1.3.dist-info/RECORD
