Metadata-Version: 2.4
Name: ros-rcl-yaml-param-parser
Version: 10.1.3
Summary: A ROS 2 package that parses YAML parameter files to populate C data structures used for node initialization.
Requires-Dist: ros-rmw~=7.8.2
Requires-Dist: ros-libyaml-vendor~=1.7.1
Requires-Dist: ros-rcutils~=6.9.8
Dynamic: description
Dynamic: description-content-type
Dynamic: requires-dist
Dynamic: summary
